CONTRIBUTORS.txt
MANIFEST.in
README.txt
setup.py
collective/__init__.py
collective.easytemplate.egg-info/PKG-INFO
collective.easytemplate.egg-info/SOURCES.txt
collective.easytemplate.egg-info/dependency_links.txt
collective.easytemplate.egg-info/entry_points.txt
collective.easytemplate.egg-info/namespace_packages.txt
collective.easytemplate.egg-info/not-zip-safe
collective.easytemplate.egg-info/requires.txt
collective.easytemplate.egg-info/top_level.txt
collective/easytemplate/.__init__.py.un~
collective/easytemplate/.engine.py.un~
collective/easytemplate/__init__.py
collective/easytemplate/compile_po.sh
collective/easytemplate/config.py
collective/easytemplate/configure.zcml
collective/easytemplate/engine.py
collective/easytemplate/fields.py
collective/easytemplate/interfaces.py
collective/easytemplate/messages.py
collective/easytemplate/tagconfig.py
collective/easytemplate/utils.py
collective/easytemplate/actions/__init__.py
collective/easytemplate/actions/configure.zcml
collective/easytemplate/actions/mail.py
collective/easytemplate/browser/__init__.py
collective/easytemplate/browser/configure.zcml
collective/easytemplate/browser/portlets/__init__.py
collective/easytemplate/browser/portlets/configure.zcml
collective/easytemplate/browser/portlets/interfaces.py
collective/easytemplate/browser/portlets/templated.py
collective/easytemplate/browser/portlets/templated_portlet.pt
collective/easytemplate/content/.TemplatedDocument.py.un~
collective/easytemplate/content/TemplatedDocument.py
collective/easytemplate/content/__init__.py
collective/easytemplate/content/configure.zcml
collective/easytemplate/locales/collective.easytemplate.pot
collective/easytemplate/locales/fi/LC_MESSAGES/collective.easytemplate.mo
collective/easytemplate/locales/fi/LC_MESSAGES/collective.easytemplate.po
collective/easytemplate/locales/nl/LC_MESSAGES/collective.easytemplate.mo
collective/easytemplate/locales/nl/LC_MESSAGES/collective.easytemplate.po
collective/easytemplate/profiles/default/factorytool.xml
collective/easytemplate/profiles/default/portlets.xml
collective/easytemplate/profiles/default/types.xml
collective/easytemplate/profiles/default/types/TemplatedDocument.xml
collective/easytemplate/tags/.views.py.un~
collective/easytemplate/tags/__init__.py
collective/easytemplate/tags/content.py
collective/easytemplate/tags/i18n.py
