Metadata-Version: 1.0
Name: collective.easytemplate
Version: 0.8.0
Summary: Dynamic HTML generation and scripting of pages, content rules, portlets and emails
Home-page: http://plone.org/products/easy-template
Author: mFabrik Research Oy
Author-email: info@mfabrik.com
License: GPL
Keywords: plone cheetah jinja template kupu scripting dynamic page html
Platform: UNKNOWN
Classifier: Framework :: Plone
Classifier: Intended Audience :: Developers
Classifier: Topic :: Software Development :: Libraries :: Python Modules
Classifier: License :: OSI Approved :: GNU General Public License (GPL)
